sideeye/__init__.py
sideeye/calculate.py
sideeye/config.py
sideeye/output.py
sideeye/types.py
sideeye/data/__init__.py
sideeye/data/experiment.py
sideeye/data/fixation.py
sideeye/data/item.py
sideeye/data/point.py
sideeye/data/region.py
sideeye/data/saccade.py
sideeye/data/trial.py
sideeye/measures/__init__.py
sideeye/measures/helpers.py
sideeye/measures/trial.py
sideeye/measures/region/__init__.py
sideeye/measures/region/boolean.py
sideeye/measures/region/duration.py
sideeye/measures/region/other.py
sideeye/parser/__init__.py
sideeye/parser/asc.py
sideeye/parser/da1.py
sideeye/parser/experiment.py
sideeye/parser/region.py
sideeye-1.0.0a13.data/scripts/sideeye
sideeye-1.0.0a13.dist-info/LICENSE
sideeye-1.0.0a13.dist-info/METADATA
sideeye-1.0.0a13.dist-info/WHEEL
sideeye-1.0.0a13.dist-info/top_level.txt
sideeye-1.0.0a13.dist-info/RECORD
