Metadata-Version: 2.1
Name: sideeye
Version: 1.0.0a13
Summary: Library for analyzing eye-tracking-while-reading data
Home-page: https://github.com/amnda-d/sideeye
Author: Amanda Doucette
Author-email: sideeye@amnda.me
License: MIT
Project-URL: Documentation, https://sideeye.readthedocs.io/en/latest/
Keywords: eyetracking eye-tracking da1 psycholinguistics linguistics psychology eyetrack
Platform: UNKNOWN
Classifier: Development Status :: 3 - Alpha
Classifier: Intended Audience :: Science/Research
Classifier: Topic :: Scientific/Engineering :: Information Analysis
Classifier: Programming Language :: Python :: 3.6
Classifier: Programming Language :: Python :: 3.7
Classifier: Programming Language :: Python :: 3.8
Requires-Python: >=3.6
Requires-Dist: typing
Requires-Dist: mypy
Requires-Dist: mypy-extensions
Provides-Extra: dev
Requires-Dist: nose2 ; extra == 'dev'
Requires-Dist: pylint ; extra == 'dev'
Provides-Extra: test
Requires-Dist: nose2 ; extra == 'test'
Requires-Dist: pylint ; extra == 'test'
